setup.py
nextf1race/__init__.py
nextf1race/nextf1race.py
nextf1race.egg-info/PKG-INFO
nextf1race.egg-info/SOURCES.txt
nextf1race.egg-info/dependency_links.txt
nextf1race.egg-info/entry_points.txt
nextf1race.egg-info/top_level.txt
race_data/2016.json
race_data/2017.json
race_data/2018.json
race_data/__init__.py
race_data/circuits.json
race_data/circuits_temp.json
race_data/info.py