Metadata-Version: 1.1
Name: nextf1race
Version: 0.1.3
Summary: A command tool to show where and when the next Formula 1 race is.
Home-page: https://github.com/WillSkywalker/nextf1race
Author: Will Skywalker
Author-email: cxbats@gmail.com
License: Apache 2.0
Keywords: f1 race Formula One motorsport
Platform: UNKNOWN
Classifier: Development Status :: 4 - Beta
Classifier: Intended Audience :: End Users/Desktop
Classifier: Topic :: Utilities
Classifier: License :: OSI Approved :: Apache Software License
Classifier: Programming Language :: Python :: 2
Classifier: Programming Language :: Python :: 2.4
Classifier: Programming Language :: Python :: 2.5
Classifier: Programming Language :: Python :: 2.6
Classifier: Programming Language :: Python :: 2.7
Classifier: Programming Language :: Python :: 3
Classifier: Programming Language :: Python :: 3.2
Classifier: Programming Language :: Python :: 3.3
Classifier: Programming Language :: Python :: 3.4
Classifier: Programming Language :: Python :: 3.5
